clean/__init__.py
clean/clean.py
clean/constants.py
clean/html_stripper.py
neon_goby_Saleswhale-0.0.1.dist-info/METADATA
neon_goby_Saleswhale-0.0.1.dist-info/WHEEL
neon_goby_Saleswhale-0.0.1.dist-info/top_level.txt
neon_goby_Saleswhale-0.0.1.dist-info/RECORD
