Metadata-Version: 2.1
Name: neon-goby-Saleswhale
Version: 0.0.1
Summary: A simple package to clean email bodies
Home-page: https://github.com/pypa/sampleproject
Author: HiiYL
Author-email: hii@saleswhale.com
License: UNKNOWN
Platform: UNKNOWN
Classifier: Programming Language :: Python :: 3
Classifier: Operating System :: OS Independent
Requires-Python: >=3.6
